pyprf_motion
