Metadata-Version: 1.0
Name: pyprf-motion
Version: 1.0.3
Summary: Population receptive field analysis for motion-sensitive                     early- and mid-level visual cortex.
Home-page: https://github.com/MSchnei/pyprf_motion
Author: Marian Schneider, Ingo Marquardt
Author-email: marian.schneider@maastrichtuniversity.nl
License: GNU General Public License Version 3
Keywords: pRF,fMRI,retinotopy
Platform: UNKNOWN
